jupyter_contrib_core/__init__.py
jupyter_contrib_core/application.py
jupyter_contrib_core/notebook_compat/__init__.py
jupyter_contrib_core/notebook_compat/nbextensions.py
jupyter_contrib_core/notebook_compat/serverextensions.py
jupyter_contrib_core/notebook_compat/_compat/__init__.py
jupyter_contrib_core/notebook_compat/_compat/nbextensions.py
jupyter_contrib_core/notebook_compat/_compat/serverextensions.py
jupyter_contrib_core/testing_utils/__init__.py
jupyter_contrib_core/testing_utils/jupyter_env.py
jupyter_contrib_core-0.4.0.data/scripts/jupyter-contrib
jupyter_contrib_core-0.4.0.dist-info/LICENSE.txt
jupyter_contrib_core-0.4.0.dist-info/METADATA
jupyter_contrib_core-0.4.0.dist-info/WHEEL
jupyter_contrib_core-0.4.0.dist-info/entry_points.txt
jupyter_contrib_core-0.4.0.dist-info/top_level.txt
jupyter_contrib_core-0.4.0.dist-info/zip-safe
jupyter_contrib_core-0.4.0.dist-info/RECORD
