Metadata-Version: 2.1
Name: jupyter_contrib_core
Version: 0.4.0
Summary: Common utilities for jupyter-contrib projects.
Home-page: https://github.com/jupyter-contrib/jupyter_contrib_core
Download-URL: https://github.com/jupyter-contrib/jupyter_contrib_core/tarball/0.4.0
Author: jcb91, jupyter-contrib developers
Author-email: joshuacookebarnes@gmail.com
License: BSD 3-clause
Keywords: Jupyter,notebook
Platform: any
Classifier: Intended Audience :: End Users/Desktop
Classifier: Intended Audience :: Science/Research
Classifier: License :: OSI Approved :: BSD License
Classifier: Natural Language :: English
Classifier: Operating System :: OS Independent
Classifier: Programming Language :: JavaScript
Classifier: Programming Language :: Python
Classifier: Programming Language :: Python :: 3
Classifier: Topic :: Utilities
Provides-Extra: testing_utils
License-File: LICENSE.txt
